vocus_sagemaker_utils/__init__.py
vocus_sagemaker_utils/_nbdev.py
vocus_sagemaker_utils/core.py
vocus_sagemaker_utils/read_csv_from_s3.py
vocus_sagemaker_utils/read_data_from_s3.py
vocus_sagemaker_utils/s3_data_utils.py
vocus_sagemaker_utils-0.0.5.dist-info/LICENSE
vocus_sagemaker_utils-0.0.5.dist-info/METADATA
vocus_sagemaker_utils-0.0.5.dist-info/WHEEL
vocus_sagemaker_utils-0.0.5.dist-info/entry_points.txt
vocus_sagemaker_utils-0.0.5.dist-info/top_level.txt
vocus_sagemaker_utils-0.0.5.dist-info/RECORD
