Metadata-Version: 2.1
Name: vocus-sagemaker-utils
Version: 0.0.5
Summary: Vocus Sagemaker M/L Utilities package
Home-page: https://gitlab.vocus.com.au/Analytics/machine-learning-platform//vocus_sagemaker_utils/tree/master/
Author: Alex Jarman
Author-email: alex.jarman@vocus.com.au
License: Apache Software License 2.0
Keywords: machine learning,jupyter notebook
Platform: UNKNOWN
Classifier: Development Status :: 3 - Alpha
Classifier: Intended Audience :: Developers
Classifier: Natural Language :: English
Classifier: Programming Language :: Python :: 3.6
Classifier: Programming Language :: Python :: 3.7
Classifier: Programming Language :: Python :: 3.8
Classifier: License :: OSI Approved :: Apache Software License
Requires-Python: >=3.6
Requires-Dist: pandas (>=1.1.5)
Requires-Dist: boto (>=2.49.0)
Requires-Dist: boto3 (>=1.17.21)
Requires-Dist: botocore (>=1.20.53)
